materia_epd/__init__.py
materia_epd/__main__.py
materia_epd/_version.py
materia_epd/cli.py
materia_epd/resources.py
materia_epd/skeleton.py
materia_epd/core/constants.py
materia_epd/core/errors.py
materia_epd/core/physics.py
materia_epd/core/utils.py
materia_epd/data/__init__.py
materia_epd/data/indicator_synonyms.json
materia_epd/data/regions_mapping.json
materia_epd/data/locations/ABW.json
materia_epd/data/locations/AFG.json
materia_epd/data/locations/AGO.json
materia_epd/data/locations/AIA.json
materia_epd/data/locations/ALA.json
materia_epd/data/locations/ALB.json
materia_epd/data/locations/AND.json
materia_epd/data/locations/ARE.json
materia_epd/data/locations/ARG.json
materia_epd/data/locations/ARM.json
materia_epd/data/locations/ASM.json
materia_epd/data/locations/ATF.json
materia_epd/data/locations/ATG.json
materia_epd/data/locations/AUS.json
materia_epd/data/locations/AUT.json
materia_epd/data/locations/AZE.json
materia_epd/data/locations/Africa.json
materia_epd/data/locations/Americas.json
materia_epd/data/locations/Asia.json
materia_epd/data/locations/Australia and New Zealand.json
materia_epd/data/locations/BDI.json
materia_epd/data/locations/BEL.json
materia_epd/data/locations/BEN.json
materia_epd/data/locations/BES.json
materia_epd/data/locations/BFA.json
materia_epd/data/locations/BGD.json
materia_epd/data/locations/BGR.json
materia_epd/data/locations/BHR.json
materia_epd/data/locations/BHS.json
materia_epd/data/locations/BIH.json
materia_epd/data/locations/BLM.json
materia_epd/data/locations/BLR.json
materia_epd/data/locations/BLZ.json
materia_epd/data/locations/BMU.json
materia_epd/data/locations/BOL.json
materia_epd/data/locations/BRA.json
materia_epd/data/locations/BRB.json
materia_epd/data/locations/BRN.json
materia_epd/data/locations/BTN.json
materia_epd/data/locations/BVT.json
materia_epd/data/locations/BWA.json
materia_epd/data/locations/CAF.json
materia_epd/data/locations/CAN.json
materia_epd/data/locations/CCK.json
materia_epd-0.4.0.dist-info/licenses/LICENSE.txt
materia_epd-0.4.0.dist-info/METADATA
materia_epd-0.4.0.dist-info/WHEEL
materia_epd-0.4.0.dist-info/top_level.txt
materia_epd-0.4.0.dist-info/RECORD
