Metadata-Version: 2.4
Name: materia-epd
Version: 0.4.0
Summary: Generic EPD Aggregator
Author-email: Paul Baustert <p.m.baustert@gmail.com>
License-Expression: MIT
Classifier: Programming Language :: Python :: 3
Classifier: Programming Language :: Python :: 3.10
Classifier: Programming Language :: Python :: 3.11
Classifier: Programming Language :: Python :: 3.12
Classifier: Operating System :: OS Independent
Requires-Python: >=3.10
License-File: LICENSE.txt
Requires-Dist: click
Requires-Dist: numpy
Requires-Dist: pandas
Requires-Dist: pycountry
Requires-Dist: comtradeapicall
Provides-Extra: dev
Requires-Dist: black==23.9.1; extra == "dev"
Requires-Dist: flake8==6.1.0; extra == "dev"
Requires-Dist: pytest==7.4.2; extra == "dev"
Requires-Dist: pytest-cov==4.1.0; extra == "dev"
Requires-Dist: pre-commit==3.4.0; extra == "dev"
Requires-Dist: deptry; extra == "dev"
Requires-Dist: coverage-badge; extra == "dev"
Requires-Dist: sphinx; extra == "dev"
Dynamic: license-file
